setup.py
wash.py
WASH.egg-info/PKG-INFO
WASH.egg-info/SOURCES.txt
WASH.egg-info/dependency_links.txt
WASH.egg-info/entry_points.txt
WASH.egg-info/requires.txt
WASH.egg-info/top_level.txt