Metadata-Version: 1.0
Name: WASH
Version: 1.6
Summary: Wolfram|Alpha interactive shell
Home-page: https://pypi.python.org/pypi/WASH
Author: Cody Brocious
Author-email: cody.brocious@gmail.com
License: CC0
Platform: UNKNOWN
